LICENSE
oddrn_generator/__init__.py
oddrn_generator/exceptions.py
oddrn_generator/generators.py
oddrn_generator/path_models.py
oddrn_generator/server_models.py
oddrn_generator/utils/__init__.py
oddrn_generator/utils/external_generators.py
oddrn_generator-0.1.103.dist-info/LICENSE
oddrn_generator-0.1.103.dist-info/WHEEL
oddrn_generator-0.1.103.dist-info/METADATA
oddrn_generator-0.1.103.dist-info/RECORD
