Metadata-Version: 2.1
Name: oddrn-generator
Version: 0.1.103
Summary: Open Data Discovery Resource Name Generator
Home-page: https://github.com/opendatadiscovery/oddrn-generator
License: Apache-2.0
Keywords: oddrn,opendatadiscovery
Author: Open Data Discovery
Author-email: pypi@opendatadiscovery.org
Requires-Python: >=3.9,<4.0
Classifier: License :: OSI Approved :: Apache Software License
Classifier: Programming Language :: Python :: 3
Classifier: Programming Language :: Python :: 3.9
Classifier: Programming Language :: Python :: 3.10
Classifier: Programming Language :: Python :: 3.11
Requires-Dist: pluggy (>=1.4.0,<2.0.0)
Requires-Dist: pydantic (>=2.7.0,<3.0.0)
Requires-Dist: pydantic-core (>=2.18.1,<3.0.0)
Requires-Dist: pydantic-settings (>=2.2.1,<3.0.0)
Project-URL: Repository, https://github.com/opendatadiscovery/oddrn-generator
